MANIFEST.in
requirements.txt
setup.py
version.py
icePick/__init__.py
icePick/exception.py
icePick/order.py
icePick/parser.py
icePick/picker.py
icePick/recorder.py
icePick.egg-info/PKG-INFO
icePick.egg-info/SOURCES.txt
icePick.egg-info/dependency_links.txt
icePick.egg-info/requires.txt
icePick.egg-info/top_level.txt
tests/__init__.py
tests/config.py
tests/test_order.py
tests/test_parser.py
tests/test_picker.py
tests/test_recorder.py