Metadata-Version: 1.1
Name: icePick
Version: 0.0.5
Summary: icePick is a All in one Package library for easy Scraping
Home-page: https://github.com/teitei-tk/ice-pick
Author: teitei-tk
Author-email: teitei.tk@gmail.com
License: MIT
Download-URL: https://github.com/teitei-tk/ice-pick/archive/master.tar.gz
Keywords: scraping
Platform: UNKNOWN
Classifier: Development Status :: 3 - Alpha
Classifier: License :: OSI Approved :: MIT License
Classifier: Programming Language :: Python
Classifier: Programming Language :: Python :: 3
Classifier: Programming Language :: Python :: 3 :: Only
Classifier: Topic :: Software Development
Classifier: Topic :: Software Development :: Libraries
Classifier: Topic :: Software Development :: Libraries :: Python Modules
